README.rst
pyproject.toml
setup.py
python/SQCommon/__init__.py
python/SQCommon/_objective.py
python/SQCommon/_result.py
python/SQCommon/_stats.py
python/SQCommon/_version.py
python/SQCommon.egg-info/PKG-INFO
python/SQCommon.egg-info/SOURCES.txt
python/SQCommon.egg-info/dependency_links.txt
python/SQCommon.egg-info/requires.txt
python/SQCommon.egg-info/top_level.txt
test/test_common.py